noteworthy/__init__.py
noteworthy/cli.hy
noteworthy/dictviewer.hy
noteworthy/foundry.hy
noteworthy/mcp_server.hy
noteworthy/pipelines.hy
noteworthy/util.hy
nwy-0.2.2.dist-info/licenses/COPYING
nwy-0.2.2.dist-info/METADATA
nwy-0.2.2.dist-info/WHEEL
nwy-0.2.2.dist-info/entry_points.txt
nwy-0.2.2.dist-info/top_level.txt
nwy-0.2.2.dist-info/RECORD
