Metadata-Version: 2.4
Name: nwy
Version: 0.2.2
Summary: A knowledge management system, using RAG, like a meta-zettelkasten.
Author-email: Ati Sharma <ati+noteworthy@agalmic.ltd>
License:                     GNU AFFERO GENERAL PUBLIC LICENSE
Project-URL: Repository, https://github.com/atisharma/noteworthy
Keywords: hy,hylang,utilities,llm,openai
Classifier: Development Status :: 4 - Beta
Classifier: License :: OSI Approved :: GNU Affero General Public License v3 or later (AGPLv3+)
Classifier: Programming Language :: Python :: 3
Classifier: Programming Language :: Python :: 3.12
Classifier: Programming Language :: Python :: 3.13
Classifier: Programming Language :: Python :: 3.14
Classifier: Programming Language :: Lisp
Classifier: Topic :: Software Development :: Libraries
Classifier: Topic :: Scientific/Engineering :: Artificial Intelligence
Requires-Python: >=3.12
License-File: COPYING
Requires-Dist: arxiv-to-prompt
Requires-Dist: fvdb>=0.1.8
Requires-Dist: hy>=1.1.0
Requires-Dist: hyrule
Requires-Dist: hyjinx[llm]>=1.1.1
Requires-Dist: mcp
Requires-Dist: pymupdf
Requires-Dist: trag>=0.0.14
Requires-Dist: tqdm
Dynamic: license-file
